<?xml version="1.0" encoding="utf-8"?><Sync><!--CloudBox Presenter by ungap AB. http://www.ungap.com--><!--UTC TimeStamps--><Version>feb-2015</Version><Unit>A0CEC80ADDEE</Unit><Timeline><MediaClip><TimeStamp>2021-04-14 07:49:19.2604</TimeStamp><Duration>00:02:00</Duration><ElementID>cmd</ElementID><MimeType>text/plain</MimeType><Payload>SHOW BREAKOUT</Payload><GUID>76249f5f-f2ef-410e-b5cb-88f7578e24b1</GUID></MediaClip><MediaClip><TimeStamp>2021-04-14 07:49:20.2604</TimeStamp><Duration>00:02:00</Duration><ElementID>cmd</ElementID><MimeType>text/plain</MimeType><Payload>HIDE BREAKOUT</Payload><GUID>40726d96-430e-4a35-9fc5-cd3712a22e1c</GUID></MediaClip><MediaClip><TimeStamp>2021-04-14 07:49:21.2604</TimeStamp><Duration>00:02:00</Duration><ElementID>cmd</ElementID><MimeType>text/plain</MimeType><Payload>SHOW QNA</Payload><GUID>75857fec-4b71-45b2-8d0e-6dbe69c1991e</GUID></MediaClip><MediaClip><TimeStamp>2021-04-14 07:49:22.2604</TimeStamp><Duration>00:02:00</Duration><ElementID>cmd</ElementID><MimeType>text/plain</MimeType><Payload>HIDE QNA</Payload><GUID>18916462-e865-4b45-8d4b-41e032523a33</GUID></MediaClip></Timeline></Sync>